fotosort/VERSION
fotosort/__init__.py
fotosort/controller.py
fotosort/imgutils.py
fotosort/ui.py
fotosort/images/noimage.png
fotosort/qml/ShortcutMenuItem.qml
fotosort/qml/main.qml
fotosort-1.3.2.data/scripts/fotosort
fotosort-1.3.2.dist-info/LICENSE
fotosort-1.3.2.dist-info/METADATA
fotosort-1.3.2.dist-info/WHEEL
fotosort-1.3.2.dist-info/top_level.txt
fotosort-1.3.2.dist-info/RECORD
