Metadata-Version: 2.1
Name: fotosort
Version: 1.3.2
Summary: Fotosort is a program for quickly copying or moving pictures from different events into different folders.
Home-page: https://github.com/kalsan/fotosort
Author: Sandro Kalbermatter
Author-email: 
License: GPLv3
Classifier: Programming Language :: Python :: 3
Classifier: License :: OSI Approved :: GNU General Public License v3 or later (GPLv3+)
Classifier: Operating System :: OS Independent
License-File: LICENSE
Requires-Dist: pillow
Requires-Dist: pyyaml
Requires-Dist: pyside6
Requires-Dist: appdirs
